helica/__init__.py
helica/Likelihood/__init__.py
helica/Likelihood/LensLikelihood/__init__.py
helica/Likelihood/LensLikelihood/ddt_likelihood.py
helica/Likelihood/LensLikelihood/dependent_param_likelihood.py
helica/Likelihood/LensLikelihood/image_position_likelihood.py
helica/Likelihood/LensLikelihood/prior_likelihood.py
helica-0.1.0.dist-info/licenses/AUTHORS.rst
helica-0.1.0.dist-info/licenses/LICENSE
helica-0.1.0.dist-info/METADATA
helica-0.1.0.dist-info/WHEEL
helica-0.1.0.dist-info/entry_points.txt
helica-0.1.0.dist-info/top_level.txt
helica-0.1.0.dist-info/RECORD
